icanc/__init__.py
icanc/icanc.py
icanc/commands/__init__.py
icanc/commands/ci.py
icanc/commands/create.py
icanc/commands/init.py
icanc/commands/submit.py
icanc/commands/test.py
icanc/commands/udebug.py
icanc/commands/common/__init__.py
icanc/commands/common/exception.py
icanc/commands/common/paths.py
icanc/commands/common/rc.py
icanc/commands/tools/__init__.py
icanc/commands/tools/auth.py
icanc/commands/tools/builder.py
icanc/commands/tools/preprocessor.py
icanc/commands/tools/runner.py
icanc/commands/tools/udebug.py
icanc/commands/tools/writer.py
icanc/data/.gitignore
icanc/data/LICENSE
icanc/data/README.md
icanc/data/icancrc.toml
icanc/data/include/icanc.h
icanc/data/problems/beecrowd/1000/solution.c
icanc/data/problems/beecrowd/1000/testcases.toml
icanc/data/templates/main.c
icanc-0.6.5.dist-info/licenses/LICENSE
icanc-0.6.5.dist-info/METADATA
icanc-0.6.5.dist-info/WHEEL
icanc-0.6.5.dist-info/entry_points.txt
icanc-0.6.5.dist-info/top_level.txt
icanc-0.6.5.dist-info/RECORD
