Metadata-Version: 2.4
Name: icanc
Version: 0.6.5
Summary: A C preprocessor and command line utility for leetcode.
Author-email: voxelstack <voxelstack@gmail.com>
Project-URL: Homepage, https://github.com/voxelstack/icanc
Project-URL: Source, https://github.com/voxelstack/icanc
Keywords: leetcode,c
License-File: LICENSE
Requires-Dist: click==8.*
Requires-Dist: pyperclip==1.*
Requires-Dist: watchdog==4.*
Requires-Dist: tomli_w==1.*
Requires-Dist: keyring==25.*
Requires-Dist: requests==2.*
Dynamic: license-file
